timetrack_slg/__init__.py
timetrack_slg-0.1.11.data/scripts/install-timetrack-slg
timetrack_slg-0.1.11.data/scripts/timetrack-consolidate-slg
timetrack_slg-0.1.11.data/scripts/timetrack-slg
timetrack_slg-0.1.11.dist-info/METADATA
timetrack_slg-0.1.11.dist-info/WHEEL
timetrack_slg-0.1.11.dist-info/top_level.txt
timetrack_slg-0.1.11.dist-info/RECORD
