Metadata-Version: 2.1
Name: timetrack-slg
Version: 0.1.11
Summary: Timetracking tools that provide the data for use with timetrack.slgotting.com
Home-page: UNKNOWN
License: UNKNOWN
Platform: UNKNOWN
Requires-Python: >=3.6.3
Requires-Dist: logger-slg (==0.3.5)
Requires-Dist: PyYAML (==6.0)
